<?xml version="1.0" encoding="UTF-8"?>
<beans xmlns="http://www.springframework.org/schema/beans"
       xmlns:xsi="http://www.w3.org/2001/XMLSchema-instance"
       xmlns:aop="http://www.springframework.org/schema/aop"
       xsi:schemaLocation="http://www.springframework.org/schema/beans
       https://www.springframework.org/schema/beans/spring-beans.xsd
       http://www.springframework.org/schema/aop
       https://www.springframework.org/schema/aop/spring-aop.xsd">

    <!--注册bean-->
    <bean id="userService" class="study.qi.service.UserServiceImp"/>
    <bean id="log" class="study.qi.log.Log"/>
    <bean id="afterLog" class="study.qi.log.AfterLog"/>

    <!--配置app
        需要导入aop的配置
        xmlns:aop="http://www.springframework.org/schema/aop"
        http://www.springframework.org/schema/aop
        https://www.springframework.org/schema/aop/spring-aop.xsd
    -->

    <!--实现AOP方式三：使用注解实现-->
    <bean id="annotationPointCut" class="study.qi.config.AnnotationPointCut"/>
    <!--开启AOP注解支持-->
    <aop:aspectj-autoproxy/>


    <!--实现AOP方式一：使用Spring原生的API-->
<!--    <aop:config>
        &lt;!&ndash;切入点：需要在哪里去执行
            expression：表达式：execution(要执行的位置！* * * *)
        &ndash;&gt;
        <aop:pointcut id="pointcut" expression="execution(* study.qi.service.UserServiceImp.*(..))"/>

        &lt;!&ndash;执行环绕增强
            将log类切入到pointcut中execution中的方法里
        &ndash;&gt;
        <aop:advisor advice-ref="log" pointcut-ref="pointcut"/>
        <aop:advisor advice-ref="afterLog" pointcut-ref="pointcut"/>
    </aop:config>-->


    <!--实现AOP方式二：自定义类-->
<!--    <bean id="diy" class="study.qi.config.DiyPointCut"/>-->

<!--    <aop:config>-->
<!--        &lt;!&ndash;自定义切面，ref：要引用的类&ndash;&gt;-->
<!--        <aop:aspect ref="diy">-->
<!--            &lt;!&ndash;切入点&ndash;&gt;-->
<!--            <aop:pointcut id="point" expression="execution(* study.qi.service.UserServiceImp.*(..))"/>-->
<!--            &lt;!&ndash;通知&ndash;&gt;-->
<!--            <aop:before method="before" pointcut-ref="point"/>-->
<!--            <aop:after method="after" pointcut-ref="point"/>-->
<!--        </aop:aspect>-->
<!--    </aop:config>-->


</beans>